Metadata-Version: 1.1
Name: cmsplugin-objects
Version: 1.0
Summary: Extend django-cms with admin form links, editing object from the toolbar
Home-page: https://github.com/doctormo/django-cmsplugin-objects
Author: Martin Owens
Author-email: doctormo@gmail.com
License: LGPLv3
Platform: linux
Classifier: Development Status :: 5 - Production/Stable
Classifier: Development Status :: 6 - Mature
Classifier: Intended Audience :: Developers
Classifier: Intended Audience :: Information Technology
Classifier: Intended Audience :: System Administrators
Classifier: Programming Language :: Python
Classifier: Programming Language :: Python :: 2.7
